{
    "name": "sensor-immersion",
    "version": "0.0.0",
    "description": "",
    "dependencies": {
        "core": "*",
        "radio": "*"
    },
    "files": [
        "README.md",
        "main.blocks",
        "main.ts",
        "Tutorial_Sound_Data.md",
        "Tutorial_Sound_Display.md",
        "magnetometer_display_field_strength.md",
        "magnetometer_metal_detector.ts",
        "Tutorial_Environmental_Data.md",
        "magnetometer_modified_metal_detector.md",
        "magnetometer_metal_detector.md",
        "magnetometer_display_magnetic_field_radio_two_microbits_and_simulator.md"
    ],
    "testFiles": [
        "test.ts"
    ],
    "public": true,
    "supportedTargets": [
        "microbit"
    ],
    "preferredEditor": "tsprj"
}
